greetnow/__init__.py
greetnow/generic.py
greetnow/evening/__init__.py
greetnow/evening/even_greet.py
greetnow/morning/__init__.py
greetnow/morning/mng_greet.py
greetnow/noon/__init__.py
greetnow/noon/noon_greet.py
greetnow-1.0.1.dist-info/METADATA
greetnow-1.0.1.dist-info/WHEEL
greetnow-1.0.1.dist-info/top_level.txt
greetnow-1.0.1.dist-info/RECORD
