Metadata-Version: 2.1
Name: greetnow
Version: 1.0.1
Summary: Greet now is a simple package which provides different types of greetings
Home-page: https://fourofour.org
Author: fourofour
Author-email: gorishabhio@email.com
